IsPycharmRun/IsPycharmRun.py
IsPycharmRun/__init__.py
IsPycharmRun-1.1.dist-info/METADATA
IsPycharmRun-1.1.dist-info/WHEEL
IsPycharmRun-1.1.dist-info/top_level.txt
IsPycharmRun-1.1.dist-info/RECORD
