Metadata-Version: 2.1
Name: IsPycharmRun
Version: 1.1
Summary: Define a decorator, identify the pycharm running environment, and call the same method in different ways
Home-page: https://gitee.com/shi_bo_xuan/testSuite
Author: Boxuan Shi
Author-email: shi425@126.com
License: UNKNOWN
Platform: UNKNOWN
Classifier: Programming Language :: Python :: 3
Classifier: License :: OSI Approved :: MIT License
Classifier: Operating System :: OS Independent
